cntkx/__init__.py
cntkx/layers/__init__.py
cntkx/layers/blocks.py
cntkx/layers/layers.py
cntkx/layers/sequence.py
cntkx/layers/models/__init__.py
cntkx/layers/models/attention.py
cntkx/layers/models/language.py
cntkx/layers/models/vision.py
cntkx/layers/tests/__init__.py
cntkx/layers/tests/attention_tests.py
cntkx/layers/tests/blocks_performance.py
cntkx/layers/tests/layers_test.py
cntkx/layers/tests/models_test.py
cntkx/layers/tests/qrnn.py
cntkx/layers/tests/test_blocks.py
cntkx/layers/tests/test_sequence.py
cntkx/learners/__init__.py
cntkx/learners/tests/__init__.py
cntkx/learners/tests/test_clr.py
cntkx/learners/tests/test_learners.py
cntkx/losses/__init__.py
cntkx/losses/tests/__init__.py
cntkx/losses/tests/losses_test.py
cntkx/losses/tests/mixture_density_network.py
cntkx/misc/__init__.py
cntkx/misc/tests/__init__.py
cntkx/misc/tests/test_ctc_encoder.py
cntkx/models/__init__.py
cntkx/ops/__init__.py
cntkx/ops/random/__init__.py
cntkx/ops/random/tests/__init__.py
cntkx/ops/random/tests/test_random_ops.py
cntkx/ops/sequence/__init__.py
cntkx/ops/sequence/tests/__init__.py
cntkx/ops/sequence/tests/seq_ops_test.py
cntkx/ops/tests/__init__.py
cntkx/ops/tests/ops_test.py
cntkx-0.1.54.dist-info/LICENSE
cntkx-0.1.54.dist-info/METADATA
cntkx-0.1.54.dist-info/WHEEL
cntkx-0.1.54.dist-info/top_level.txt
cntkx-0.1.54.dist-info/RECORD
