Metadata-Version: 2.1
Name: cntkx
Version: 0.1.54
Summary: Extension library of Microsoft Cognitive Toolkit
Home-page: https://github.com/delzac/cntkx
Author: delzac
Author-email: delzac.jh@gmail.com
License: UNKNOWN
Platform: UNKNOWN
Classifier: Programming Language :: Python :: 3
Classifier: License :: OSI Approved :: MIT License
Classifier: Operating System :: OS Independent
Requires-Python: >=3.6
